{
  "generated_at": "2026-07-16T02:02:57.706183+08:00",
  "total_titles_processed": 410,
  "failed_sources": [],
  "trends": [
    {
      "keyword_group": "华为 ADS 鸿蒙智行 问界 尊界 智界 享界 阿维塔 智驾",
      "match_count": 1,
      "titles": [
        {
          "title": "如何评价 Q2 全球智能手机出货量同比下滑，小米跌幅最大，三星、苹果、华为逆势上涨？",
          "url": "https://www.zhihu.com/question/2060476741349646921",
          "source": "知乎",
          "ranks": [
            2
          ],
          "is_new": false,
          "appearance_count": 2,
          "time_info": "[00时19分 ~ 02时02分]"
        }
      ]
    }
  ],
  "report_image_url": "https://joyce677.github.io/TrendRadar/img/news.jpg"
}