{
  "generated_at": "2026-02-02T22:02:21.825789+08:00",
  "total_titles_processed": 1661,
  "failed_sources": [],
  "trends": [
    {
      "keyword_group": "华为 ADS 鸿蒙智行 问界 尊界 智界 享界 阿维塔 智驾",
      "match_count": 7,
      "titles": [
        {
          "title": "同属国产百万级高端增程，为何黑科技拉满的 2.0T 仰望 U8，还卖不过饱受争议的 1.5T 尊界 S800？",
          "url": "https://www.zhihu.com/question/2001070081015318180",
          "source": "知乎",
          "ranks": [
            3,
            5,
            7,
            15,
            17,
            18,
            20
          ],
          "is_new": false,
          "appearance_count": 10,
          "time_info": "[09时52分 ~ 18时41分]"
        },
        {
          "title": "多家车企新年首月销量出炉，鸿蒙智行交付增长超六成，理想交付新车超 2.7 万辆，如何评价各家表现？",
          "url": "https://www.zhihu.com/question/2001246362277258317",
          "source": "知乎",
          "ranks": [
            8,
            14,
            12,
            9
          ],
          "is_new": false,
          "appearance_count": 9,
          "time_info": "[16时39分 ~ 22时02分]"
        },
        {
          "title": "华为云发布业界首个智慧病理云边端解决方案",
          "url": "https://wallstreetcn.com/livenews/3047822",
          "source": "华尔街见闻-快讯",
          "ranks": [
            6,
            7,
            22
          ],
          "is_new": false,
          "appearance_count": 8,
          "time_info": "[00时25分 ~ 07时22分]"
        },
        {
          "title": "余承东官宣问界M6即将登场",
          "url": "https://www.toutiao.com/trending/7602095285845839370/",
          "source": "今日头条",
          "ranks": [
            20
          ],
          "is_new": false,
          "appearance_count": 2,
          "time_info": "[12时22分 ~ 14时02分]"
        },
        {
          "title": "华为联合周大福推出黄金耳机配饰",
          "url": "https://wallstreetcn.com/livenews/3048309",
          "source": "华尔街见闻-快讯",
          "ranks": [
            11
          ],
          "is_new": false,
          "appearance_count": 1,
          "time_info": "19时34分"
        },
        {
          "title": "华为余承东：问界M6即将登场",
          "url": "https://wallstreetcn.com/livenews/3047909",
          "source": "华尔街见闻-快讯",
          "ranks": [
            19
          ],
          "is_new": false,
          "appearance_count": 1,
          "time_info": "09时53分"
        },
        {
          "title": "华为手机1月销量市场份额提升至18.6%，位居第一",
          "url": "https://wallstreetcn.com/livenews/3048236",
          "source": "华尔街见闻-快讯",
          "ranks": [
            23
          ],
          "is_new": false,
          "appearance_count": 1,
          "time_info": "17时44分"
        }
      ]
    }
  ],
  "report_image_url": "https://joyce677.github.io/TrendRadar/img/news.jpg"
}